LICENSE
MANIFEST.in
README.rst
janitor.py
setup.py
Janitor.egg-info/PKG-INFO
Janitor.egg-info/SOURCES.txt
Janitor.egg-info/dependency_links.txt
Janitor.egg-info/entry_points.txt
Janitor.egg-info/not-zip-safe
Janitor.egg-info/requires.txt
Janitor.egg-info/top_level.txt